{"discoAPIPort":31057,"repoAPIPort":32057,"initialNodes":[{"name":"f23","ip":"127.0.0.1","distance":0,"discoAPIPort":31023,"repoAPIPort":32023},{"name":"f23","ip":"127.0.0.1","distance":0,"discoAPIPort":31023,"repoAPIPort":32023},{"name":"f34","ip":"127.0.0.1","distance":0,"discoAPIPort":31034,"repoAPIPort":32034},{"name":"f40","ip":"127.0.0.1","distance":0,"discoAPIPort":31040,"repoAPIPort":32040},{"name":"f21","ip":"127.0.0.1","distance":0,"discoAPIPort":31021,"repoAPIPort":32021}],"maxPing":10,"nodeID":"f57","nodeType":"servicenode","pingPeriod":3000,"testMode":true,"cheatyMinimalPing":10,"cheatyMinimalPingMap":{"e0":14.278502,"f0":19.548456,"f1":37.500458,"f10":8.954461,"f100":5.198697,"f101":36.645046,"f102":33.109867,"f103":37.019974,"f104":41.056442,"f105":50.490723,"f106":29.477476,"f107":14.542195,"f108":18.354378,"f109":30.44421,"f11":11.640889,"f110":25.896862,"f111":9.206021,"f112":17.938002,"f113":34.52986,"f114":23.144304,"f115":11.808843,"f116":26.09825,"f117":37.33751,"f118":30.794079,"f119":14.228214,"f12":8.319781,"f120":32.051437,"f121":17.422903,"f122":16.754036,"f123":8.239586,"f124":34.572613,"f13":32.045784,"f14":23.441877,"f15":25.175217,"f16":37.68823,"f17":6.5760527,"f18":7.0760207,"f19":17.196745,"f2":16.690073,"f20":5.712477,"f21":24.52211,"f22":32.664463,"f23":12.72422,"f24":1.9697473,"f25":54.057552,"f26":18.370323,"f27":3.87264,"f28":33.99168,"f29":40.291386,"f3":32.888454,"f30":21.925747,"f31":13.645131,"f32":25.49304,"f33":8.177354,"f34":7.1487646,"f35":39.570904,"f36":28.691486,"f37":19.977915,"f38":20.73976,"f39":5.194269,"f4":36.384,"f40":2.1427503,"f41":18.02332,"f42":5.4716315,"f43":22.144165,"f44":17.501698,"f45":14.232728,"f46":30.105507,"f47":5.3791957,"f48":10.961522,"f49":17.821852,"f5":12.804038,"f50":29.56367,"f51":16.557215,"f52":9.934989,"f53":25.81984,"f54":34.844505,"f55":7.063504,"f56":6.5010786,"f58":20.661684,"f59":25.127432,"f6":18.477005,"f60":42.054626,"f61":33.580364,"f62":14.929161,"f63":29.494558,"f64":7.5587597,"f65":21.33005,"f66":22.104939,"f67":9.082656,"f68":33.92708,"f69":36.375946,"f7":4.783892,"f70":21.995634,"f71":26.303802,"f72":39.591206,"f73":43.322353,"f74":38.483376,"f75":37.334724,"f76":23.356697,"f77":15.954087,"f78":27.670578,"f79":36.23041,"f8":6.72052,"f80":10.387929,"f81":16.196003,"f82":18.065489,"f83":36.71488,"f84":7.6440716,"f85":36.277126,"f86":38.912186,"f87":16.652884,"f88":10.792032,"f89":16.534313,"f9":14.823824,"f90":6.9036727,"f91":13.6401415,"f92":17.524841,"f93":36.099506,"f94":38.44235,"f95":11.005282,"f96":15.41723,"f97":13.405255,"f98":15.952625,"f99":12.872635},"BasicComponentDefs":{"Component 1":[{"ApiVersion":"v1/beta","Kind":"ComponentDefinition","Metadata":{"Name":"Implementation 1.2","Labels":{},"Annotations":null},"Spec":{"Workload":{"Type":"Container","Definition":{"ApiVersion":"","Kind":""}},"Schematic":{"Definition":{"name":"TestApp","image":"gitlab.ilabt.imec.be:4567/fledge/benchmark/dash:1.0.0-capstan","command":["./dashserver.so"],"resources":{"limits":{"cpu":"500m","memory":"300M"},"requests":{"cpu":"100m","memory":"100M"}},"imagePullPolicy":"Always"},"Params":null,"BaseComponent":"Component 1","BaseResources":null,"MaxResources":null}}}],"Component 15":[{"ApiVersion":"v1/beta","Kind":"ComponentDefinition","Metadata":{"Name":"Implementation 15.2","Labels":{},"Annotations":null},"Spec":{"Workload":{"Type":"Container","Definition":{"ApiVersion":"","Kind":""}},"Schematic":{"Definition":{"name":"TestApp","image":"gitlab.ilabt.imec.be:4567/fledge/benchmark/dash:1.0.0-capstan","command":["./dashserver.so"],"resources":{"limits":{"cpu":"500m","memory":"300M"},"requests":{"cpu":"100m","memory":"100M"}},"imagePullPolicy":"Always"},"Params":null,"BaseComponent":"Component 15","BaseResources":null,"MaxResources":null}}}],"Component 38":[{"ApiVersion":"v1/beta","Kind":"ComponentDefinition","Metadata":{"Name":"Implementation 38.2","Labels":{},"Annotations":null},"Spec":{"Workload":{"Type":"Container","Definition":{"ApiVersion":"","Kind":""}},"Schematic":{"Definition":{"name":"TestApp","image":"gitlab.ilabt.imec.be:4567/fledge/benchmark/dash:1.0.0-capstan","command":["./dashserver.so"],"resources":{"limits":{"cpu":"500m","memory":"300M"},"requests":{"cpu":"100m","memory":"100M"}},"imagePullPolicy":"Always"},"Params":null,"BaseComponent":"Component 38","BaseResources":null,"MaxResources":null}}}],"Component 45":[{"ApiVersion":"v1/beta","Kind":"ComponentDefinition","Metadata":{"Name":"Implementation 45.1","Labels":{},"Annotations":null},"Spec":{"Workload":{"Type":"Container","Definition":{"ApiVersion":"","Kind":""}},"Schematic":{"Definition":{"name":"TestApp","image":"gitlab.ilabt.imec.be:4567/fledge/benchmark/dash:1.0.0-capstan","command":["./dashserver.so"],"resources":{"limits":{"cpu":"500m","memory":"300M"},"requests":{"cpu":"100m","memory":"100M"}},"imagePullPolicy":"Always"},"Params":null,"BaseComponent":"Component 45","BaseResources":null,"MaxResources":null}}}],"Component 7":[{"ApiVersion":"v1/beta","Kind":"ComponentDefinition","Metadata":{"Name":"Implementation 7.1","Labels":{},"Annotations":null},"Spec":{"Workload":{"Type":"Container","Definition":{"ApiVersion":"","Kind":""}},"Schematic":{"Definition":{"name":"TestApp","image":"gitlab.ilabt.imec.be:4567/fledge/benchmark/dash:1.0.0-capstan","command":["./dashserver.so"],"resources":{"limits":{"cpu":"500m","memory":"300M"},"requests":{"cpu":"100m","memory":"100M"}},"imagePullPolicy":"Always"},"Params":null,"BaseComponent":"Component 7","BaseResources":null,"MaxResources":null}}}]}}