{"discoAPIPort":31036,"repoAPIPort":32036,"initialNodes":[{"name":"f16","ip":"127.0.0.1","distance":0,"discoAPIPort":31016,"repoAPIPort":32016},{"name":"f9","ip":"127.0.0.1","distance":0,"discoAPIPort":31009,"repoAPIPort":32009},{"name":"f4","ip":"127.0.0.1","distance":0,"discoAPIPort":31004,"repoAPIPort":32004},{"name":"f2","ip":"127.0.0.1","distance":0,"discoAPIPort":31002,"repoAPIPort":32002},{"name":"f24","ip":"127.0.0.1","distance":0,"discoAPIPort":31024,"repoAPIPort":32024}],"maxPing":8,"nodeID":"f36","nodeType":"servicenode","pingPeriod":3000,"testMode":true,"cheatyMinimalPing":10,"cheatyMinimalPingMap":{"e0":47.331825,"f0":22.921925,"f1":31.810848,"f10":26.17445,"f11":59.583008,"f12":5.971244,"f13":47.298714,"f14":24.398365,"f15":26.422338,"f16":25.012094,"f17":7.447521,"f18":56.075554,"f19":34.58144,"f2":48.00462,"f20":16.933937,"f21":17.028328,"f22":27.09532,"f23":15.510096,"f24":32.69723,"f25":49.2273,"f26":43.17547,"f27":27.931215,"f28":45.932735,"f29":31.94874,"f3":45.41496,"f30":22.947254,"f31":36.92333,"f32":24.615114,"f33":53.476128,"f34":24.542847,"f35":6.8187356,"f37":36.523262,"f38":37.951824,"f39":32.265827,"f4":21.472101,"f40":25.756004,"f41":13.170614,"f42":12.033108,"f43":29.048931,"f44":27.94974,"f45":19.531096,"f46":16.028137,"f47":27.497272,"f48":21.825302,"f49":27.568993,"f5":49.77561,"f50":33.84644,"f51":10.797871,"f52":39.848804,"f53":25.792376,"f54":47.58768,"f55":53.974884,"f56":20.514282,"f57":48.167152,"f58":27.91097,"f59":31.313435,"f6":4.065288,"f7":45.36887,"f8":12.166288,"f9":29.991032},"BasicComponentDefs":{"Component 1":[{"ApiVersion":"v1/beta","Kind":"ComponentDefinition","Metadata":{"Name":"Implementation 1.1","Labels":{},"Annotations":null},"Spec":{"Workload":{"Type":"Container","Definition":{"ApiVersion":"","Kind":""}},"Schematic":{"Definition":{"name":"TestApp","image":"gitlab.ilabt.imec.be:4567/fledge/benchmark/dash:1.0.0-capstan","command":["./dashserver.so"],"resources":{"limits":{"cpu":"500m","memory":"300M"},"requests":{"cpu":"100m","memory":"100M"}},"imagePullPolicy":"Always"},"Params":null,"BaseComponent":"Component 1","BaseResources":null,"MaxResources":null}}},{"ApiVersion":"v1/beta","Kind":"ComponentDefinition","Metadata":{"Name":"Implementation 1.1","Labels":{},"Annotations":null},"Spec":{"Workload":{"Type":"Container","Definition":{"ApiVersion":"","Kind":""}},"Schematic":{"Definition":{"name":"TestApp","image":"gitlab.ilabt.imec.be:4567/fledge/benchmark/dash:1.0.0-capstan","command":["./dashserver.so"],"resources":{"limits":{"cpu":"500m","memory":"300M"},"requests":{"cpu":"100m","memory":"100M"}},"imagePullPolicy":"Always"},"Params":null,"BaseComponent":"Component 1","BaseResources":null,"MaxResources":null}}},{"ApiVersion":"v1/beta","Kind":"ComponentDefinition","Metadata":{"Name":"Implementation 1.1","Labels":{},"Annotations":null},"Spec":{"Workload":{"Type":"Container","Definition":{"ApiVersion":"","Kind":""}},"Schematic":{"Definition":{"name":"TestApp","image":"gitlab.ilabt.imec.be:4567/fledge/benchmark/dash:1.0.0-capstan","command":["./dashserver.so"],"resources":{"limits":{"cpu":"500m","memory":"300M"},"requests":{"cpu":"100m","memory":"100M"}},"imagePullPolicy":"Always"},"Params":null,"BaseComponent":"Component 1","BaseResources":null,"MaxResources":null}}}],"Component 2":[{"ApiVersion":"v1/beta","Kind":"ComponentDefinition","Metadata":{"Name":"Implementation 2.1","Labels":{},"Annotations":null},"Spec":{"Workload":{"Type":"Container","Definition":{"ApiVersion":"","Kind":""}},"Schematic":{"Definition":{"name":"TestApp","image":"gitlab.ilabt.imec.be:4567/fledge/benchmark/dash:1.0.0-capstan","command":["./dashserver.so"],"resources":{"limits":{"cpu":"500m","memory":"300M"},"requests":{"cpu":"100m","memory":"100M"}},"imagePullPolicy":"Always"},"Params":null,"BaseComponent":"Component 2","BaseResources":null,"MaxResources":null}}},{"ApiVersion":"v1/beta","Kind":"ComponentDefinition","Metadata":{"Name":"Implementation 2.1","Labels":{},"Annotations":null},"Spec":{"Workload":{"Type":"Container","Definition":{"ApiVersion":"","Kind":""}},"Schematic":{"Definition":{"name":"TestApp","image":"gitlab.ilabt.imec.be:4567/fledge/benchmark/dash:1.0.0-capstan","command":["./dashserver.so"],"resources":{"limits":{"cpu":"500m","memory":"300M"},"requests":{"cpu":"100m","memory":"100M"}},"imagePullPolicy":"Always"},"Params":null,"BaseComponent":"Component 2","BaseResources":null,"MaxResources":null}}}]}}