{"discoAPIPort":31041,"repoAPIPort":32041,"initialNodes":[{"name":"f18","ip":"127.0.0.1","distance":0,"discoAPIPort":31018,"repoAPIPort":32018},{"name":"f25","ip":"127.0.0.1","distance":0,"discoAPIPort":31025,"repoAPIPort":32025},{"name":"f10","ip":"127.0.0.1","distance":0,"discoAPIPort":31010,"repoAPIPort":32010},{"name":"f9","ip":"127.0.0.1","distance":0,"discoAPIPort":31009,"repoAPIPort":32009},{"name":"f23","ip":"127.0.0.1","distance":0,"discoAPIPort":31023,"repoAPIPort":32023}],"maxPing":8,"nodeID":"f41","nodeType":"servicenode","pingPeriod":3000,"testMode":true,"cheatyMinimalPing":10,"cheatyMinimalPingMap":{"e0":52.895573,"f0":7.1873612,"f1":25.485052,"f10":32.715004,"f11":48.67868,"f12":10.081337,"f13":52.43909,"f14":30.520296,"f15":27.866734,"f16":12.1571,"f17":11.185793,"f18":50.553394,"f19":42.16219,"f2":40.27004,"f20":22.984322,"f21":19.579449,"f22":31.98205,"f23":21.219551,"f24":25.602373,"f25":45.787697,"f26":53.728508,"f27":33.85568,"f28":33.119774,"f29":23.501978,"f3":42.6811,"f30":23.014791,"f31":41.982365,"f32":16.6324,"f33":52.63796,"f34":5.498993,"f35":17.792807,"f36":13.170614,"f37":52.612747,"f38":37.58663,"f39":35.043625,"f4":7.6902423,"f40":31.442862,"f42":3.259022,"f43":13.286255,"f44":27.855059,"f45":9.998612,"f46":20.982643,"f47":18.650784,"f48":9.863381,"f49":15.111118,"f5":59.863117,"f50":35.755054,"f51":18.063026,"f52":41.108116,"f53":29.978857,"f54":52.60585,"f55":45.570866,"f56":22.822157,"f57":58.920128,"f58":18.890844,"f59":15.521797,"f6":17.171936,"f7":39.264626,"f8":1.6294181,"f9":20.41953},"BasicComponentDefs":{"Component 1":[{"ApiVersion":"v1/beta","Kind":"ComponentDefinition","Metadata":{"Name":"Implementation 1.1","Labels":{},"Annotations":null},"Spec":{"Workload":{"Type":"Container","Definition":{"ApiVersion":"","Kind":""}},"Schematic":{"Definition":{"name":"TestApp","image":"gitlab.ilabt.imec.be:4567/fledge/benchmark/dash:1.0.0-capstan","command":["./dashserver.so"],"resources":{"limits":{"cpu":"500m","memory":"300M"},"requests":{"cpu":"100m","memory":"100M"}},"imagePullPolicy":"Always"},"Params":null,"BaseComponent":"Component 1","BaseResources":null,"MaxResources":null}}},{"ApiVersion":"v1/beta","Kind":"ComponentDefinition","Metadata":{"Name":"Implementation 1.1","Labels":{},"Annotations":null},"Spec":{"Workload":{"Type":"Container","Definition":{"ApiVersion":"","Kind":""}},"Schematic":{"Definition":{"name":"TestApp","image":"gitlab.ilabt.imec.be:4567/fledge/benchmark/dash:1.0.0-capstan","command":["./dashserver.so"],"resources":{"limits":{"cpu":"500m","memory":"300M"},"requests":{"cpu":"100m","memory":"100M"}},"imagePullPolicy":"Always"},"Params":null,"BaseComponent":"Component 1","BaseResources":null,"MaxResources":null}}},{"ApiVersion":"v1/beta","Kind":"ComponentDefinition","Metadata":{"Name":"Implementation 1.1","Labels":{},"Annotations":null},"Spec":{"Workload":{"Type":"Container","Definition":{"ApiVersion":"","Kind":""}},"Schematic":{"Definition":{"name":"TestApp","image":"gitlab.ilabt.imec.be:4567/fledge/benchmark/dash:1.0.0-capstan","command":["./dashserver.so"],"resources":{"limits":{"cpu":"500m","memory":"300M"},"requests":{"cpu":"100m","memory":"100M"}},"imagePullPolicy":"Always"},"Params":null,"BaseComponent":"Component 1","BaseResources":null,"MaxResources":null}}},{"ApiVersion":"v1/beta","Kind":"ComponentDefinition","Metadata":{"Name":"Implementation 1.1","Labels":{},"Annotations":null},"Spec":{"Workload":{"Type":"Container","Definition":{"ApiVersion":"","Kind":""}},"Schematic":{"Definition":{"name":"TestApp","image":"gitlab.ilabt.imec.be:4567/fledge/benchmark/dash:1.0.0-capstan","command":["./dashserver.so"],"resources":{"limits":{"cpu":"500m","memory":"300M"},"requests":{"cpu":"100m","memory":"100M"}},"imagePullPolicy":"Always"},"Params":null,"BaseComponent":"Component 1","BaseResources":null,"MaxResources":null}}}],"Component 2":[{"ApiVersion":"v1/beta","Kind":"ComponentDefinition","Metadata":{"Name":"Implementation 2.1","Labels":{},"Annotations":null},"Spec":{"Workload":{"Type":"Container","Definition":{"ApiVersion":"","Kind":""}},"Schematic":{"Definition":{"name":"TestApp","image":"gitlab.ilabt.imec.be:4567/fledge/benchmark/dash:1.0.0-capstan","command":["./dashserver.so"],"resources":{"limits":{"cpu":"500m","memory":"300M"},"requests":{"cpu":"100m","memory":"100M"}},"imagePullPolicy":"Always"},"Params":null,"BaseComponent":"Component 2","BaseResources":null,"MaxResources":null}}}]}}