{"discoAPIPort":31058,"repoAPIPort":32058,"initialNodes":[{"name":"f1","ip":"127.0.0.1","distance":0,"discoAPIPort":31001,"repoAPIPort":32001},{"name":"f53","ip":"127.0.0.1","distance":0,"discoAPIPort":31053,"repoAPIPort":32053},{"name":"f22","ip":"127.0.0.1","distance":0,"discoAPIPort":31022,"repoAPIPort":32022},{"name":"f26","ip":"127.0.0.1","distance":0,"discoAPIPort":31026,"repoAPIPort":32026},{"name":"f5","ip":"127.0.0.1","distance":0,"discoAPIPort":31005,"repoAPIPort":32005}],"maxPing":8,"nodeID":"f58","nodeType":"servicenode","pingPeriod":3000,"testMode":true,"cheatyMinimalPing":10,"cheatyMinimalPingMap":{"e0":52.61282,"f0":14.219678,"f1":14.459047,"f10":28.030663,"f11":41.86614,"f12":34.341377,"f13":39.111004,"f14":37.00171,"f15":30.77115,"f16":11.933003,"f17":35.83676,"f18":60.882313,"f19":31.373121,"f2":52.851185,"f20":28.252794,"f21":23.959204,"f22":45.96755,"f23":27.971832,"f24":25.688856,"f25":55.259724,"f26":48.741543,"f27":30.398676,"f28":36.922928,"f29":2.753397,"f3":35.171864,"f30":18.420637,"f31":51.160725,"f32":17.249077,"f33":35.701973,"f34":13.192173,"f35":29.677473,"f36":27.91097,"f37":61.349895,"f38":54.03817,"f39":25.33495,"f4":14.768829,"f40":34.359585,"f41":18.890844,"f42":22.594679,"f43":5.409185,"f44":30.646803,"f45":10.952898,"f46":33.117367,"f47":18.251703,"f48":10.521108,"f49":3.0949357,"f5":52.940105,"f50":47.396236,"f51":38.944324,"f52":52.46357,"f53":34.765995,"f54":47.819572,"f55":45.870884,"f56":27.15144,"f57":36.31799,"f59":7.4418497,"f6":36.167355,"f7":35.32566,"f8":21.352175,"f9":9.011026},"BasicComponentDefs":{"Component 1":[{"ApiVersion":"v1/beta","Kind":"ComponentDefinition","Metadata":{"Name":"Implementation 1.1","Labels":{},"Annotations":null},"Spec":{"Workload":{"Type":"Container","Definition":{"ApiVersion":"","Kind":""}},"Schematic":{"Definition":{"name":"TestApp","image":"gitlab.ilabt.imec.be:4567/fledge/benchmark/dash:1.0.0-capstan","command":["./dashserver.so"],"resources":{"limits":{"cpu":"500m","memory":"300M"},"requests":{"cpu":"100m","memory":"100M"}},"imagePullPolicy":"Always"},"Params":null,"BaseComponent":"Component 1","BaseResources":null,"MaxResources":null}}}],"Component 2":[{"ApiVersion":"v1/beta","Kind":"ComponentDefinition","Metadata":{"Name":"Implementation 2.1","Labels":{},"Annotations":null},"Spec":{"Workload":{"Type":"Container","Definition":{"ApiVersion":"","Kind":""}},"Schematic":{"Definition":{"name":"TestApp","image":"gitlab.ilabt.imec.be:4567/fledge/benchmark/dash:1.0.0-capstan","command":["./dashserver.so"],"resources":{"limits":{"cpu":"500m","memory":"300M"},"requests":{"cpu":"100m","memory":"100M"}},"imagePullPolicy":"Always"},"Params":null,"BaseComponent":"Component 2","BaseResources":null,"MaxResources":null}}},{"ApiVersion":"v1/beta","Kind":"ComponentDefinition","Metadata":{"Name":"Implementation 2.1","Labels":{},"Annotations":null},"Spec":{"Workload":{"Type":"Container","Definition":{"ApiVersion":"","Kind":""}},"Schematic":{"Definition":{"name":"TestApp","image":"gitlab.ilabt.imec.be:4567/fledge/benchmark/dash:1.0.0-capstan","command":["./dashserver.so"],"resources":{"limits":{"cpu":"500m","memory":"300M"},"requests":{"cpu":"100m","memory":"100M"}},"imagePullPolicy":"Always"},"Params":null,"BaseComponent":"Component 2","BaseResources":null,"MaxResources":null}}},{"ApiVersion":"v1/beta","Kind":"ComponentDefinition","Metadata":{"Name":"Implementation 2.1","Labels":{},"Annotations":null},"Spec":{"Workload":{"Type":"Container","Definition":{"ApiVersion":"","Kind":""}},"Schematic":{"Definition":{"name":"TestApp","image":"gitlab.ilabt.imec.be:4567/fledge/benchmark/dash:1.0.0-capstan","command":["./dashserver.so"],"resources":{"limits":{"cpu":"500m","memory":"300M"},"requests":{"cpu":"100m","memory":"100M"}},"imagePullPolicy":"Always"},"Params":null,"BaseComponent":"Component 2","BaseResources":null,"MaxResources":null}}},{"ApiVersion":"v1/beta","Kind":"ComponentDefinition","Metadata":{"Name":"Implementation 2.1","Labels":{},"Annotations":null},"Spec":{"Workload":{"Type":"Container","Definition":{"ApiVersion":"","Kind":""}},"Schematic":{"Definition":{"name":"TestApp","image":"gitlab.ilabt.imec.be:4567/fledge/benchmark/dash:1.0.0-capstan","command":["./dashserver.so"],"resources":{"limits":{"cpu":"500m","memory":"300M"},"requests":{"cpu":"100m","memory":"100M"}},"imagePullPolicy":"Always"},"Params":null,"BaseComponent":"Component 2","BaseResources":null,"MaxResources":null}}}]}}