{"discoAPIPort":31058,"repoAPIPort":32058,"initialNodes":[{"name":"f14","ip":"127.0.0.1","distance":0,"discoAPIPort":31014,"repoAPIPort":32014},{"name":"f30","ip":"127.0.0.1","distance":0,"discoAPIPort":31030,"repoAPIPort":32030},{"name":"f5","ip":"127.0.0.1","distance":0,"discoAPIPort":31005,"repoAPIPort":32005},{"name":"f31","ip":"127.0.0.1","distance":0,"discoAPIPort":31031,"repoAPIPort":32031},{"name":"f49","ip":"127.0.0.1","distance":0,"discoAPIPort":31049,"repoAPIPort":32049}],"maxPing":20,"nodeID":"f58","nodeType":"servicenode","pingPeriod":3000,"testMode":true,"cheatyMinimalPing":10,"cheatyMinimalPingMap":{"e0":32.001976,"f0":19.697512,"f1":16.714025,"f10":9.689984,"f11":27.141026,"f12":11.1898365,"f13":26.1859,"f14":26.241364,"f15":33.510456,"f16":31.217093,"f17":21.055717,"f18":20.600077,"f19":23.52143,"f2":5.2354407,"f20":3.9573987,"f21":13.152013,"f22":19.535814,"f23":20.647882,"f24":15.843741,"f25":21.582493,"f26":14.733338,"f27":45.549633,"f28":36.389137,"f29":29.512331,"f3":23.993093,"f30":23.222353,"f31":31.567074,"f32":21.11678,"f33":7.194057,"f34":4.287047,"f35":5.134148,"f36":23.027702,"f37":5.822981,"f38":19.945196,"f39":23.811674,"f4":7.9938602,"f40":36.96393,"f41":28.069386,"f42":40.314274,"f43":25.568882,"f44":44.471546,"f45":24.99056,"f46":35.814075,"f47":3.8012025,"f48":29.904993,"f49":17.439737,"f5":50.6004,"f50":22.389704,"f51":22.571123,"f52":41.83094,"f53":10.319526,"f54":25.596876,"f55":9.320135,"f56":9.413734,"f57":10.07632,"f59":8.790177,"f6":14.584836,"f60":50.080982,"f61":33.299347,"f62":29.122736,"f63":36.739086,"f64":16.658909,"f65":33.873352,"f66":24.013159,"f67":21.018936,"f68":19.709587,"f69":50.608112,"f7":17.117224,"f70":22.204018,"f71":32.79272,"f72":8.823207,"f73":11.229257,"f74":15.578704,"f75":11.249909,"f76":32.061478,"f77":20.844742,"f78":15.396563,"f79":41.19772,"f8":15.106149,"f80":30.665363,"f81":20.05076,"f82":25.656107,"f83":45.691105,"f84":45.84891,"f85":8.00041,"f86":23.588884,"f87":7.606989,"f88":29.75057,"f89":31.372362,"f9":25.159498,"f90":41.213066,"f91":39.446167,"f92":26.12619,"f93":22.596601,"f94":45.871674,"f95":31.509245,"f96":20.028639,"f97":16.268324,"f98":25.41508,"f99":19.411123},"BasicComponentDefs":{"Component 20":[{"ApiVersion":"v1/beta","Kind":"ComponentDefinition","Metadata":{"Name":"Implementation 20.2","Labels":{},"Annotations":null},"Spec":{"Workload":{"Type":"Container","Definition":{"ApiVersion":"","Kind":""}},"Schematic":{"Definition":{"name":"TestApp","image":"gitlab.ilabt.imec.be:4567/fledge/benchmark/dash:1.0.0-capstan","command":["./dashserver.so"],"resources":{"limits":{"cpu":"500m","memory":"300M"},"requests":{"cpu":"100m","memory":"100M"}},"imagePullPolicy":"Always"},"Params":null,"BaseComponent":"Component 20","BaseResources":null,"MaxResources":null}}}],"Component 31":[{"ApiVersion":"v1/beta","Kind":"ComponentDefinition","Metadata":{"Name":"Implementation 31.2","Labels":{},"Annotations":null},"Spec":{"Workload":{"Type":"Container","Definition":{"ApiVersion":"","Kind":""}},"Schematic":{"Definition":{"name":"TestApp","image":"gitlab.ilabt.imec.be:4567/fledge/benchmark/dash:1.0.0-capstan","command":["./dashserver.so"],"resources":{"limits":{"cpu":"500m","memory":"300M"},"requests":{"cpu":"100m","memory":"100M"}},"imagePullPolicy":"Always"},"Params":null,"BaseComponent":"Component 31","BaseResources":null,"MaxResources":null}}}],"Component 5":[{"ApiVersion":"v1/beta","Kind":"ComponentDefinition","Metadata":{"Name":"Implementation 5.1","Labels":{},"Annotations":null},"Spec":{"Workload":{"Type":"Container","Definition":{"ApiVersion":"","Kind":""}},"Schematic":{"Definition":{"name":"TestApp","image":"gitlab.ilabt.imec.be:4567/fledge/benchmark/dash:1.0.0-capstan","command":["./dashserver.so"],"resources":{"limits":{"cpu":"500m","memory":"300M"},"requests":{"cpu":"100m","memory":"100M"}},"imagePullPolicy":"Always"},"Params":null,"BaseComponent":"Component 5","BaseResources":null,"MaxResources":null}}}],"Component 7":[{"ApiVersion":"v1/beta","Kind":"ComponentDefinition","Metadata":{"Name":"Implementation 7.1","Labels":{},"Annotations":null},"Spec":{"Workload":{"Type":"Container","Definition":{"ApiVersion":"","Kind":""}},"Schematic":{"Definition":{"name":"TestApp","image":"gitlab.ilabt.imec.be:4567/fledge/benchmark/dash:1.0.0-capstan","command":["./dashserver.so"],"resources":{"limits":{"cpu":"500m","memory":"300M"},"requests":{"cpu":"100m","memory":"100M"}},"imagePullPolicy":"Always"},"Params":null,"BaseComponent":"Component 7","BaseResources":null,"MaxResources":null}}}],"Component 8":[{"ApiVersion":"v1/beta","Kind":"ComponentDefinition","Metadata":{"Name":"Implementation 8.1","Labels":{},"Annotations":null},"Spec":{"Workload":{"Type":"Container","Definition":{"ApiVersion":"","Kind":""}},"Schematic":{"Definition":{"name":"TestApp","image":"gitlab.ilabt.imec.be:4567/fledge/benchmark/dash:1.0.0-capstan","command":["./dashserver.so"],"resources":{"limits":{"cpu":"500m","memory":"300M"},"requests":{"cpu":"100m","memory":"100M"}},"imagePullPolicy":"Always"},"Params":null,"BaseComponent":"Component 8","BaseResources":null,"MaxResources":null}}}]}}