{"discoAPIPort":31010,"repoAPIPort":32010,"initialNodes":[{"name":"f2","ip":"127.0.0.1","distance":0,"discoAPIPort":31002,"repoAPIPort":32002},{"name":"f8","ip":"127.0.0.1","distance":0,"discoAPIPort":31008,"repoAPIPort":32008},{"name":"f3","ip":"127.0.0.1","distance":0,"discoAPIPort":31003,"repoAPIPort":32003},{"name":"f4","ip":"127.0.0.1","distance":0,"discoAPIPort":31004,"repoAPIPort":32004},{"name":"f8","ip":"127.0.0.1","distance":0,"discoAPIPort":31008,"repoAPIPort":32008}],"maxPing":10,"nodeID":"f10","nodeType":"servicenode","pingPeriod":3000,"testMode":true,"cheatyMinimalPing":10,"cheatyMinimalPingMap":{"e0":18.76664,"f0":7.3753552,"f1":32.59991,"f100":29.86205,"f101":38.169014,"f102":12.617208,"f103":13.534131,"f104":8.596274,"f105":6.8509493,"f106":4.6248636,"f107":16.867903,"f108":14.519318,"f109":27.587904,"f11":11.3867445,"f110":13.709011,"f111":24.054008,"f112":11.832249,"f113":26.94277,"f114":20.093899,"f115":8.335864,"f116":19.886631,"f117":24.352037,"f118":18.401981,"f119":29.16647,"f12":20.030664,"f120":13.438819,"f121":27.336111,"f122":27.671415,"f123":26.900078,"f124":30.491652,"f125":7.8836,"f126":29.435904,"f127":27.21094,"f128":24.094488,"f129":5.742595,"f13":14.413163,"f130":18.739279,"f131":12.070244,"f132":14.653804,"f133":21.190092,"f134":27.51065,"f135":19.050354,"f136":21.622929,"f137":24.88651,"f138":21.26384,"f139":7.4163523,"f14":16.83817,"f140":25.905312,"f141":32.099342,"f142":24.456963,"f143":17.348494,"f144":18.946882,"f145":5.017609,"f146":19.164719,"f147":24.60888,"f148":17.217934,"f149":11.728636,"f15":32.36909,"f16":24.478313,"f17":9.605681,"f18":18.34271,"f19":13.291369,"f2":9.023077,"f20":22.792997,"f21":8.262759,"f22":2.5209723,"f23":19.84136,"f24":26.6471,"f25":22.746204,"f26":8.653172,"f27":29.187963,"f28":18.62606,"f29":21.551727,"f3":4.5273,"f30":15.136501,"f31":10.490632,"f32":27.491146,"f33":2.368007,"f34":18.563715,"f35":27.756752,"f36":18.525461,"f37":13.790056,"f38":5.6106634,"f39":22.75537,"f4":28.99905,"f40":15.594246,"f41":33.47928,"f42":12.669482,"f43":30.52656,"f44":10.252292,"f45":26.423063,"f46":24.64597,"f47":28.684198,"f48":25.990194,"f49":6.548432,"f5":5.9433794,"f50":19.543451,"f51":21.704144,"f52":26.390265,"f53":11.345297,"f54":5.466594,"f55":28.5462,"f56":24.158678,"f57":18.223661,"f58":33.0926,"f59":34.17605,"f6":16.014399,"f60":12.599217,"f61":4.394371,"f62":14.415824,"f63":30.076622,"f64":12.756866,"f65":25.92382,"f66":26.17063,"f67":22.35955,"f68":10.955994,"f69":40.24589,"f7":2.693576,"f70":33.575146,"f71":15.475081,"f72":17.101109,"f73":16.13058,"f74":34.476013,"f75":12.53686,"f76":11.801542,"f77":15.260141,"f78":20.788624,"f79":20.418465,"f8":10.847178,"f80":30.841291,"f81":34.795406,"f82":15.134821,"f83":28.749578,"f84":27.943138,"f85":28.003443,"f86":24.375456,"f87":10.172539,"f88":20.034475,"f89":6.5888634,"f9":3.6406202,"f90":16.261047,"f91":27.756657,"f92":15.329027,"f93":22.814013,"f94":31.215677,"f95":19.94347,"f96":34.704426,"f97":31.732857,"f98":21.334171,"f99":29.278978},"BasicComponentDefs":{"Component 11":[{"ApiVersion":"v1/beta","Kind":"ComponentDefinition","Metadata":{"Name":"Implementation 11.2","Labels":{},"Annotations":null},"Spec":{"Workload":{"Type":"Container","Definition":{"ApiVersion":"","Kind":""}},"Schematic":{"Definition":{"name":"TestApp","image":"gitlab.ilabt.imec.be:4567/fledge/benchmark/dash:1.0.0-capstan","command":["./dashserver.so"],"resources":{"limits":{"cpu":"500m","memory":"300M"},"requests":{"cpu":"100m","memory":"100M"}},"imagePullPolicy":"Always"},"Params":null,"BaseComponent":"Component 11","BaseResources":null,"MaxResources":null}}}],"Component 13":[{"ApiVersion":"v1/beta","Kind":"ComponentDefinition","Metadata":{"Name":"Implementation 13.1","Labels":{},"Annotations":null},"Spec":{"Workload":{"Type":"Container","Definition":{"ApiVersion":"","Kind":""}},"Schematic":{"Definition":{"name":"TestApp","image":"gitlab.ilabt.imec.be:4567/fledge/benchmark/dash:1.0.0-capstan","command":["./dashserver.so"],"resources":{"limits":{"cpu":"500m","memory":"300M"},"requests":{"cpu":"100m","memory":"100M"}},"imagePullPolicy":"Always"},"Params":null,"BaseComponent":"Component 13","BaseResources":null,"MaxResources":null}}}],"Component 25":[{"ApiVersion":"v1/beta","Kind":"ComponentDefinition","Metadata":{"Name":"Implementation 25.2","Labels":{},"Annotations":null},"Spec":{"Workload":{"Type":"Container","Definition":{"ApiVersion":"","Kind":""}},"Schematic":{"Definition":{"name":"TestApp","image":"gitlab.ilabt.imec.be:4567/fledge/benchmark/dash:1.0.0-capstan","command":["./dashserver.so"],"resources":{"limits":{"cpu":"500m","memory":"300M"},"requests":{"cpu":"100m","memory":"100M"}},"imagePullPolicy":"Always"},"Params":null,"BaseComponent":"Component 25","BaseResources":null,"MaxResources":null}}}],"Component 47":[{"ApiVersion":"v1/beta","Kind":"ComponentDefinition","Metadata":{"Name":"Implementation 47.1","Labels":{},"Annotations":null},"Spec":{"Workload":{"Type":"Container","Definition":{"ApiVersion":"","Kind":""}},"Schematic":{"Definition":{"name":"TestApp","image":"gitlab.ilabt.imec.be:4567/fledge/benchmark/dash:1.0.0-capstan","command":["./dashserver.so"],"resources":{"limits":{"cpu":"500m","memory":"300M"},"requests":{"cpu":"100m","memory":"100M"}},"imagePullPolicy":"Always"},"Params":null,"BaseComponent":"Component 47","BaseResources":null,"MaxResources":null}}}],"Component 49":[{"ApiVersion":"v1/beta","Kind":"ComponentDefinition","Metadata":{"Name":"Implementation 49.2","Labels":{},"Annotations":null},"Spec":{"Workload":{"Type":"Container","Definition":{"ApiVersion":"","Kind":""}},"Schematic":{"Definition":{"name":"TestApp","image":"gitlab.ilabt.imec.be:4567/fledge/benchmark/dash:1.0.0-capstan","command":["./dashserver.so"],"resources":{"limits":{"cpu":"500m","memory":"300M"},"requests":{"cpu":"100m","memory":"100M"}},"imagePullPolicy":"Always"},"Params":null,"BaseComponent":"Component 49","BaseResources":null,"MaxResources":null}}}]}}