{"discoAPIPort":31134,"repoAPIPort":32134,"initialNodes":[{"name":"f70","ip":"127.0.0.1","distance":0,"discoAPIPort":31070,"repoAPIPort":32070},{"name":"f97","ip":"127.0.0.1","distance":0,"discoAPIPort":31097,"repoAPIPort":32097},{"name":"f38","ip":"127.0.0.1","distance":0,"discoAPIPort":31038,"repoAPIPort":32038},{"name":"f111","ip":"127.0.0.1","distance":0,"discoAPIPort":31111,"repoAPIPort":32111},{"name":"f115","ip":"127.0.0.1","distance":0,"discoAPIPort":31115,"repoAPIPort":32115}],"maxPing":10,"nodeID":"f134","nodeType":"servicenode","pingPeriod":3000,"testMode":true,"cheatyMinimalPing":10,"cheatyMinimalPingMap":{"e0":4.007931,"f0":24.61621,"f1":54.794277,"f10":27.51065,"f100":11.440447,"f101":44.236877,"f102":21.050447,"f103":16.459352,"f104":29.792065,"f105":27.930178,"f106":30.567566,"f107":12.391003,"f108":26.568048,"f109":8.268876,"f11":13.261349,"f110":16.563372,"f111":47.193977,"f112":31.774681,"f113":9.576725,"f114":8.409245,"f115":27.995165,"f116":30.805628,"f117":55.50184,"f118":17.440039,"f119":57.9386,"f12":8.787723,"f120":24.579473,"f121":13.400831,"f122":45.39491,"f123":4.208195,"f124":60.066654,"f125":30.915865,"f126":15.35178,"f127":58.941177,"f128":37.03005,"f129":24.883715,"f13":40.72726,"f130":19.069326,"f131":46.0972,"f132":36.254196,"f133":42.70809,"f135":12.571695,"f136":48.3814,"f137":65.72227,"f138":13.079423,"f139":26.925102,"f14":14.724086,"f140":51.38273,"f141":52.652565,"f142":25.008657,"f143":19.905815,"f144":52.141033,"f145":31.195158,"f146":35.258343,"f147":3.5627337,"f148":18.672503,"f149":30.091713,"f15":60.94407,"f16":62.98617,"f17":20.295055,"f18":54.212826,"f19":39.19808,"f2":18.878475,"f20":51.29078,"f21":40.06793,"f22":25.098694,"f23":44.66467,"f24":13.293561,"f25":38.028942,"f26":34.153725,"f27":21.368776,"f28":14.497853,"f29":1.992918,"f3":34.7344,"f30":10.920532,"f31":20.078396,"f32":56.79284,"f33":22.423513,"f34":22.789791,"f35":53.72669,"f36":14.139959,"f37":21.276186,"f38":21.501503,"f39":6.315883,"f4":10.808246,"f40":38.360317,"f41":64.985344,"f42":34.122337,"f43":59.09339,"f44":39.03647,"f45":46.319115,"f46":44.70532,"f47":14.073237,"f48":24.521315,"f49":27.653023,"f5":38.820965,"f50":41.107513,"f51":4.002575,"f52":42.706474,"f53":15.465148,"f54":35.16892,"f55":55.19929,"f56":28.152142,"f57":24.819176,"f58":55.492466,"f59":21.911125,"f6":13.826436,"f60":42.905655,"f61":29.88667,"f62":32.51528,"f63":51.102535,"f64":39.70953,"f65":39.750477,"f66":8.016994,"f67":41.8091,"f68":26.665897,"f69":55.64821,"f7":27.759197,"f70":51.10008,"f71":40.742287,"f72":35.54761,"f73":24.025936,"f74":17.434095,"f75":30.111395,"f76":24.33158,"f77":26.570415,"f78":14.196674,"f79":10.419557,"f8":18.70982,"f80":64.68086,"f81":3.889008,"f82":19.235857,"f83":21.29506,"f84":57.099827,"f85":3.6014893,"f86":43.32331,"f87":12.866308,"f88":34.803753,"f89":40.021637,"f9":26.589396,"f90":25.208546,"f91":49.364643,"f92":26.134012,"f93":1.9627837,"f94":6.386156,"f95":55.846333,"f96":1.801757,"f97":56.805836,"f98":21.48502,"f99":62.427547},"BasicComponentDefs":{"Component 12":[{"ApiVersion":"v1/beta","Kind":"ComponentDefinition","Metadata":{"Name":"Implementation 12.1","Labels":{},"Annotations":null},"Spec":{"Workload":{"Type":"Container","Definition":{"ApiVersion":"","Kind":""}},"Schematic":{"Definition":{"name":"TestApp","image":"gitlab.ilabt.imec.be:4567/fledge/benchmark/dash:1.0.0-capstan","command":["./dashserver.so"],"resources":{"limits":{"cpu":"500m","memory":"300M"},"requests":{"cpu":"100m","memory":"100M"}},"imagePullPolicy":"Always"},"Params":null,"BaseComponent":"Component 12","BaseResources":null,"MaxResources":null}}}],"Component 15":[{"ApiVersion":"v1/beta","Kind":"ComponentDefinition","Metadata":{"Name":"Implementation 15.2","Labels":{},"Annotations":null},"Spec":{"Workload":{"Type":"Container","Definition":{"ApiVersion":"","Kind":""}},"Schematic":{"Definition":{"name":"TestApp","image":"gitlab.ilabt.imec.be:4567/fledge/benchmark/dash:1.0.0-capstan","command":["./dashserver.so"],"resources":{"limits":{"cpu":"500m","memory":"300M"},"requests":{"cpu":"100m","memory":"100M"}},"imagePullPolicy":"Always"},"Params":null,"BaseComponent":"Component 15","BaseResources":null,"MaxResources":null}}}],"Component 26":[{"ApiVersion":"v1/beta","Kind":"ComponentDefinition","Metadata":{"Name":"Implementation 26.2","Labels":{},"Annotations":null},"Spec":{"Workload":{"Type":"Container","Definition":{"ApiVersion":"","Kind":""}},"Schematic":{"Definition":{"name":"TestApp","image":"gitlab.ilabt.imec.be:4567/fledge/benchmark/dash:1.0.0-capstan","command":["./dashserver.so"],"resources":{"limits":{"cpu":"500m","memory":"300M"},"requests":{"cpu":"100m","memory":"100M"}},"imagePullPolicy":"Always"},"Params":null,"BaseComponent":"Component 26","BaseResources":null,"MaxResources":null}}}],"Component 39":[{"ApiVersion":"v1/beta","Kind":"ComponentDefinition","Metadata":{"Name":"Implementation 39.2","Labels":{},"Annotations":null},"Spec":{"Workload":{"Type":"Container","Definition":{"ApiVersion":"","Kind":""}},"Schematic":{"Definition":{"name":"TestApp","image":"gitlab.ilabt.imec.be:4567/fledge/benchmark/dash:1.0.0-capstan","command":["./dashserver.so"],"resources":{"limits":{"cpu":"500m","memory":"300M"},"requests":{"cpu":"100m","memory":"100M"}},"imagePullPolicy":"Always"},"Params":null,"BaseComponent":"Component 39","BaseResources":null,"MaxResources":null}}}],"Component 4":[{"ApiVersion":"v1/beta","Kind":"ComponentDefinition","Metadata":{"Name":"Implementation 4.1","Labels":{},"Annotations":null},"Spec":{"Workload":{"Type":"Container","Definition":{"ApiVersion":"","Kind":""}},"Schematic":{"Definition":{"name":"TestApp","image":"gitlab.ilabt.imec.be:4567/fledge/benchmark/dash:1.0.0-capstan","command":["./dashserver.so"],"resources":{"limits":{"cpu":"500m","memory":"300M"},"requests":{"cpu":"100m","memory":"100M"}},"imagePullPolicy":"Always"},"Params":null,"BaseComponent":"Component 4","BaseResources":null,"MaxResources":null}}}]}}