{"discoAPIPort":31044,"repoAPIPort":32044,"initialNodes":[{"name":"f34","ip":"127.0.0.1","distance":0,"discoAPIPort":31034,"repoAPIPort":32034},{"name":"f14","ip":"127.0.0.1","distance":0,"discoAPIPort":31014,"repoAPIPort":32014},{"name":"f4","ip":"127.0.0.1","distance":0,"discoAPIPort":31004,"repoAPIPort":32004},{"name":"f43","ip":"127.0.0.1","distance":0,"discoAPIPort":31043,"repoAPIPort":32043},{"name":"f19","ip":"127.0.0.1","distance":0,"discoAPIPort":31019,"repoAPIPort":32019}],"maxPing":10,"nodeID":"f44","nodeType":"servicenode","pingPeriod":3000,"testMode":true,"cheatyMinimalPing":10,"cheatyMinimalPingMap":{"e0":25.92419,"f0":18.084057,"f1":29.080599,"f10":10.252292,"f100":47.464912,"f101":40.956203,"f102":15.605519,"f103":20.344906,"f104":15.786403,"f105":6.304183,"f106":8.595311,"f107":23.076078,"f108":19.271328,"f109":40.523674,"f11":21.974493,"f110":22.115131,"f111":11.457544,"f112":6.2606907,"f113":28.031027,"f114":31.987621,"f115":7.7418537,"f116":26.901295,"f117":16.202833,"f118":31.714071,"f119":21.377943,"f12":34.569523,"f120":18.612219,"f121":28.40755,"f122":30.585123,"f123":34.414925,"f124":26.975819,"f125":4.0148616,"f126":33.616898,"f127":16.05064,"f128":30.474483,"f129":12.432186,"f13":8.250401,"f130":34.137486,"f131":4.531531,"f132":10.342599,"f133":21.675695,"f134":39.03647,"f135":26.87441,"f136":14.647997,"f137":29.697264,"f138":31.840961,"f139":5.3312354,"f14":27.230213,"f140":30.944988,"f141":20.683126,"f142":28.530695,"f143":18.974394,"f144":26.191254,"f145":9.056897,"f146":18.60551,"f147":40.724884,"f148":33.542686,"f149":19.433208,"f15":28.414349,"f16":22.577185,"f17":17.663813,"f18":13.988949,"f19":6.025693,"f2":21.389473,"f20":19.31396,"f21":9.435842,"f22":7.5352254,"f23":22.95679,"f24":33.250378,"f25":10.516492,"f26":13.228447,"f27":36.947483,"f28":27.518257,"f29":29.960669,"f3":3.7824187,"f30":25.865702,"f31":17.115313,"f32":18.6174,"f33":10.210281,"f34":24.649118,"f35":22.861597,"f36":27.592476,"f37":18.61654,"f38":15.710882,"f39":39.31491,"f4":34.29362,"f40":26.39222,"f41":20.86765,"f42":17.132786,"f43":32.404587,"f45":31.954859,"f46":21.078457,"f47":40.681335,"f48":28.032827,"f49":14.19511,"f5":5.372041,"f50":19.518892,"f51":31.391083,"f52":24.62238,"f53":24.650787,"f54":5.730419,"f55":29.880762,"f56":32.856636,"f57":24.878157,"f58":33.56192,"f59":44.767796,"f6":26.311499,"f60":4.676084,"f61":4.6874304,"f62":15.888254,"f63":27.222897,"f64":6.961794,"f65":22.78132,"f66":37.918095,"f67":22.041464,"f68":13.49433,"f69":30.421211,"f7":6.4190946,"f70":23.689005,"f71":5.681051,"f72":14.594306,"f73":22.786894,"f74":49.13595,"f75":7.3466363,"f76":12.696151,"f77":22.805437,"f78":29.791433,"f79":29.165577,"f8":20.085636,"f80":28.398918,"f81":30.430536,"f82":21.028242,"f83":34.11942,"f84":15.669373,"f85":27.993084,"f86":18.834118,"f87":17.2968,"f88":19.70838,"f89":3.781439,"f9":8.320867,"f90":20.677406,"f91":28.72018,"f92":18.85673,"f93":33.660614,"f94":46.606403,"f95":13.491691,"f96":40.61245,"f97":19.557758,"f98":21.202011,"f99":24.297297},"BasicComponentDefs":{"Component 1":[{"ApiVersion":"v1/beta","Kind":"ComponentDefinition","Metadata":{"Name":"Implementation 1.1","Labels":{},"Annotations":null},"Spec":{"Workload":{"Type":"Container","Definition":{"ApiVersion":"","Kind":""}},"Schematic":{"Definition":{"name":"TestApp","image":"gitlab.ilabt.imec.be:4567/fledge/benchmark/dash:1.0.0-capstan","command":["./dashserver.so"],"resources":{"limits":{"cpu":"500m","memory":"300M"},"requests":{"cpu":"100m","memory":"100M"}},"imagePullPolicy":"Always"},"Params":null,"BaseComponent":"Component 1","BaseResources":null,"MaxResources":null}}}],"Component 19":[{"ApiVersion":"v1/beta","Kind":"ComponentDefinition","Metadata":{"Name":"Implementation 19.1","Labels":{},"Annotations":null},"Spec":{"Workload":{"Type":"Container","Definition":{"ApiVersion":"","Kind":""}},"Schematic":{"Definition":{"name":"TestApp","image":"gitlab.ilabt.imec.be:4567/fledge/benchmark/dash:1.0.0-capstan","command":["./dashserver.so"],"resources":{"limits":{"cpu":"500m","memory":"300M"},"requests":{"cpu":"100m","memory":"100M"}},"imagePullPolicy":"Always"},"Params":null,"BaseComponent":"Component 19","BaseResources":null,"MaxResources":null}}}],"Component 29":[{"ApiVersion":"v1/beta","Kind":"ComponentDefinition","Metadata":{"Name":"Implementation 29.1","Labels":{},"Annotations":null},"Spec":{"Workload":{"Type":"Container","Definition":{"ApiVersion":"","Kind":""}},"Schematic":{"Definition":{"name":"TestApp","image":"gitlab.ilabt.imec.be:4567/fledge/benchmark/dash:1.0.0-capstan","command":["./dashserver.so"],"resources":{"limits":{"cpu":"500m","memory":"300M"},"requests":{"cpu":"100m","memory":"100M"}},"imagePullPolicy":"Always"},"Params":null,"BaseComponent":"Component 29","BaseResources":null,"MaxResources":null}}}],"Component 33":[{"ApiVersion":"v1/beta","Kind":"ComponentDefinition","Metadata":{"Name":"Implementation 33.2","Labels":{},"Annotations":null},"Spec":{"Workload":{"Type":"Container","Definition":{"ApiVersion":"","Kind":""}},"Schematic":{"Definition":{"name":"TestApp","image":"gitlab.ilabt.imec.be:4567/fledge/benchmark/dash:1.0.0-capstan","command":["./dashserver.so"],"resources":{"limits":{"cpu":"500m","memory":"300M"},"requests":{"cpu":"100m","memory":"100M"}},"imagePullPolicy":"Always"},"Params":null,"BaseComponent":"Component 33","BaseResources":null,"MaxResources":null}}}],"Component 43":[{"ApiVersion":"v1/beta","Kind":"ComponentDefinition","Metadata":{"Name":"Implementation 43.2","Labels":{},"Annotations":null},"Spec":{"Workload":{"Type":"Container","Definition":{"ApiVersion":"","Kind":""}},"Schematic":{"Definition":{"name":"TestApp","image":"gitlab.ilabt.imec.be:4567/fledge/benchmark/dash:1.0.0-capstan","command":["./dashserver.so"],"resources":{"limits":{"cpu":"500m","memory":"300M"},"requests":{"cpu":"100m","memory":"100M"}},"imagePullPolicy":"Always"},"Params":null,"BaseComponent":"Component 43","BaseResources":null,"MaxResources":null}}}]}}