{"discoAPIPort":31051,"repoAPIPort":32051,"initialNodes":[{"name":"f13","ip":"127.0.0.1","distance":0,"discoAPIPort":31013,"repoAPIPort":32013},{"name":"f41","ip":"127.0.0.1","distance":0,"discoAPIPort":31041,"repoAPIPort":32041},{"name":"f21","ip":"127.0.0.1","distance":0,"discoAPIPort":31021,"repoAPIPort":32021},{"name":"f20","ip":"127.0.0.1","distance":0,"discoAPIPort":31020,"repoAPIPort":32020},{"name":"f11","ip":"127.0.0.1","distance":0,"discoAPIPort":31011,"repoAPIPort":32011}],"maxPing":10,"nodeID":"f51","nodeType":"servicenode","pingPeriod":3000,"testMode":true,"cheatyMinimalPing":10,"cheatyMinimalPingMap":{"e0":3.1226726,"f0":16.17379,"f1":47.341236,"f10":21.704144,"f100":13.530715,"f101":52.39835,"f102":24.432156,"f103":12.170601,"f104":27.231686,"f105":25.842667,"f106":25.819376,"f107":11.222981,"f108":25.858463,"f109":8.995832,"f11":11.20792,"f110":15.424666,"f111":42.09479,"f112":31.332417,"f113":15.732588,"f114":6.3383913,"f115":28.390387,"f116":24.99613,"f117":46.98961,"f118":20.574415,"f119":44.996735,"f12":9.002421,"f120":23.343163,"f121":11.352684,"f122":57.658375,"f123":3.0853236,"f124":56.499916,"f125":36.813934,"f126":15.246546,"f127":50.10123,"f128":33.692444,"f129":27.440828,"f13":36.121002,"f130":16.709137,"f131":41.055397,"f132":45.696827,"f133":43.929806,"f134":4.002575,"f135":7.3120193,"f136":50.30207,"f137":42.770344,"f138":10.957026,"f139":29.520178,"f14":15.148891,"f140":46.26619,"f141":51.09511,"f142":32.476948,"f143":15.965911,"f144":45.61733,"f145":25.807755,"f146":40.408276,"f147":0.5571737,"f148":10.626143,"f149":27.330505,"f15":57.829674,"f16":56.3323,"f17":16.7036,"f18":54.37491,"f19":45.984413,"f2":18.02313,"f20":52.106285,"f21":32.5626,"f22":24.290552,"f23":36.765377,"f24":7.4066176,"f25":48.166954,"f26":25.13549,"f27":13.647661,"f28":11.682256,"f29":1.5769811,"f3":29.48274,"f30":10.762842,"f31":20.610111,"f32":39.500042,"f33":27.115582,"f34":20.421743,"f35":44.15026,"f36":11.135234,"f37":17.343224,"f38":19.304945,"f39":3.4882178,"f4":8.469443,"f40":35.169205,"f41":53.705025,"f42":35.376625,"f43":46.33748,"f44":31.391083,"f45":48.085518,"f46":30.105364,"f47":12.919604,"f48":19.71529,"f49":24.332458,"f5":34.08577,"f50":38.040516,"f52":39.12031,"f53":10.845103,"f54":29.65166,"f55":49.410248,"f56":19.893938,"f57":15.71072,"f58":54.228943,"f59":13.7339735,"f6":13.211114,"f60":34.989864,"f61":33.14833,"f62":28.925104,"f63":46.308277,"f64":37.55308,"f65":41.695705,"f66":14.950396,"f67":34.262962,"f68":21.429018,"f69":58.000614,"f7":26.508661,"f70":61.51726,"f71":32.98877,"f72":44.532898,"f73":17.889606,"f74":14.639429,"f75":31.917063,"f76":28.557823,"f77":25.398481,"f78":11.952683,"f79":14.266913,"f8":15.339554,"f80":61.32599,"f81":3.6943374,"f82":24.507914,"f83":15.754512,"f84":42.19296,"f85":5.3652954,"f86":57.235344,"f87":15.569602,"f88":41.269627,"f89":27.519796,"f9":28.153135,"f90":19.327473,"f91":40.959732,"f92":26.586933,"f93":2.772166,"f94":7.2289467,"f95":50.30192,"f96":5.601096,"f97":60.166813,"f98":21.159756,"f99":63.081867},"BasicComponentDefs":{"Component 14":[{"ApiVersion":"v1/beta","Kind":"ComponentDefinition","Metadata":{"Name":"Implementation 14.1","Labels":{},"Annotations":null},"Spec":{"Workload":{"Type":"Container","Definition":{"ApiVersion":"","Kind":""}},"Schematic":{"Definition":{"name":"TestApp","image":"gitlab.ilabt.imec.be:4567/fledge/benchmark/dash:1.0.0-capstan","command":["./dashserver.so"],"resources":{"limits":{"cpu":"500m","memory":"300M"},"requests":{"cpu":"100m","memory":"100M"}},"imagePullPolicy":"Always"},"Params":null,"BaseComponent":"Component 14","BaseResources":null,"MaxResources":null}}}],"Component 25":[{"ApiVersion":"v1/beta","Kind":"ComponentDefinition","Metadata":{"Name":"Implementation 25.1","Labels":{},"Annotations":null},"Spec":{"Workload":{"Type":"Container","Definition":{"ApiVersion":"","Kind":""}},"Schematic":{"Definition":{"name":"TestApp","image":"gitlab.ilabt.imec.be:4567/fledge/benchmark/dash:1.0.0-capstan","command":["./dashserver.so"],"resources":{"limits":{"cpu":"500m","memory":"300M"},"requests":{"cpu":"100m","memory":"100M"}},"imagePullPolicy":"Always"},"Params":null,"BaseComponent":"Component 25","BaseResources":null,"MaxResources":null}}}],"Component 28":[{"ApiVersion":"v1/beta","Kind":"ComponentDefinition","Metadata":{"Name":"Implementation 28.2","Labels":{},"Annotations":null},"Spec":{"Workload":{"Type":"Container","Definition":{"ApiVersion":"","Kind":""}},"Schematic":{"Definition":{"name":"TestApp","image":"gitlab.ilabt.imec.be:4567/fledge/benchmark/dash:1.0.0-capstan","command":["./dashserver.so"],"resources":{"limits":{"cpu":"500m","memory":"300M"},"requests":{"cpu":"100m","memory":"100M"}},"imagePullPolicy":"Always"},"Params":null,"BaseComponent":"Component 28","BaseResources":null,"MaxResources":null}}}],"Component 33":[{"ApiVersion":"v1/beta","Kind":"ComponentDefinition","Metadata":{"Name":"Implementation 33.1","Labels":{},"Annotations":null},"Spec":{"Workload":{"Type":"Container","Definition":{"ApiVersion":"","Kind":""}},"Schematic":{"Definition":{"name":"TestApp","image":"gitlab.ilabt.imec.be:4567/fledge/benchmark/dash:1.0.0-capstan","command":["./dashserver.so"],"resources":{"limits":{"cpu":"500m","memory":"300M"},"requests":{"cpu":"100m","memory":"100M"}},"imagePullPolicy":"Always"},"Params":null,"BaseComponent":"Component 33","BaseResources":null,"MaxResources":null}}}],"Component 44":[{"ApiVersion":"v1/beta","Kind":"ComponentDefinition","Metadata":{"Name":"Implementation 44.1","Labels":{},"Annotations":null},"Spec":{"Workload":{"Type":"Container","Definition":{"ApiVersion":"","Kind":""}},"Schematic":{"Definition":{"name":"TestApp","image":"gitlab.ilabt.imec.be:4567/fledge/benchmark/dash:1.0.0-capstan","command":["./dashserver.so"],"resources":{"limits":{"cpu":"500m","memory":"300M"},"requests":{"cpu":"100m","memory":"100M"}},"imagePullPolicy":"Always"},"Params":null,"BaseComponent":"Component 44","BaseResources":null,"MaxResources":null}}}]}}