{"discoAPIPort":31022,"repoAPIPort":32022,"initialNodes":[{"name":"f17","ip":"127.0.0.1","distance":0,"discoAPIPort":31017,"repoAPIPort":32017},{"name":"f7","ip":"127.0.0.1","distance":0,"discoAPIPort":31007,"repoAPIPort":32007},{"name":"f8","ip":"127.0.0.1","distance":0,"discoAPIPort":31008,"repoAPIPort":32008},{"name":"f2","ip":"127.0.0.1","distance":0,"discoAPIPort":31002,"repoAPIPort":32002},{"name":"f3","ip":"127.0.0.1","distance":0,"discoAPIPort":31003,"repoAPIPort":32003}],"maxPing":20,"nodeID":"f22","nodeType":"servicenode","pingPeriod":3000,"testMode":true,"cheatyMinimalPing":10,"cheatyMinimalPingMap":{"e0":31.464144,"f0":30.619793,"f1":26.415424,"f10":39.841755,"f100":31.582485,"f101":9.109367,"f102":44.502735,"f103":22.315598,"f104":40.791904,"f105":21.659262,"f106":47.397057,"f107":14.648531,"f108":58.566364,"f109":31.474539,"f11":20.240612,"f110":35.781494,"f111":30.881792,"f112":20.935865,"f113":15.528657,"f114":22.23517,"f115":34.023148,"f116":4.627844,"f117":46.593563,"f118":29.510822,"f119":49.34899,"f12":24.72131,"f120":3.9562216,"f121":24.014072,"f122":59.85403,"f123":31.646305,"f124":31.628193,"f125":34.923885,"f126":43.975513,"f127":18.750376,"f128":23.595108,"f129":26.265842,"f13":4.195934,"f130":46.798912,"f131":27.829428,"f132":15.574588,"f133":49.031643,"f134":46.871574,"f135":21.625187,"f136":25.826725,"f137":9.536612,"f138":8.969069,"f139":11.789772,"f14":32.80458,"f140":20.240633,"f141":20.158968,"f142":32.103416,"f143":12.76638,"f144":13.9289,"f145":19.579288,"f146":38.780575,"f147":33.777206,"f148":40.655506,"f149":30.876272,"f15":9.4333315,"f150":43.711433,"f151":12.099005,"f152":30.366571,"f153":24.238602,"f154":56.653492,"f155":27.153294,"f156":46.449944,"f157":22.028227,"f158":31.140884,"f159":29.990362,"f16":34.052452,"f160":34.5173,"f161":48.3244,"f162":30.540337,"f163":21.97412,"f164":35.358673,"f165":27.31013,"f166":27.778385,"f167":29.893402,"f168":16.483643,"f169":20.678968,"f17":55.828907,"f170":29.76013,"f171":34.642155,"f172":30.173632,"f173":13.244973,"f174":30.795025,"f18":11.826711,"f19":15.243902,"f2":27.406172,"f20":33.37947,"f21":27.737103,"f23":25.03021,"f24":26.117865,"f25":30.28609,"f26":20.943829,"f27":22.927547,"f28":28.173685,"f29":31.406427,"f3":45.057182,"f30":35.98915,"f31":40.714123,"f32":32.46499,"f33":38.52119,"f34":3.6971111,"f35":33.990604,"f36":32.461098,"f37":27.942488,"f38":41.76462,"f39":43.31856,"f4":19.555498,"f40":16.094568,"f41":30.239273,"f42":27.163668,"f43":43.026394,"f44":10.023923,"f45":49.47098,"f46":51.063362,"f47":29.65571,"f48":12.727841,"f49":35.40137,"f5":35.49749,"f50":28.2356,"f51":40.95631,"f52":25.128065,"f53":7.2041326,"f54":22.830854,"f55":18.18551,"f56":22.390577,"f57":35.663017,"f58":28.776651,"f59":44.002445,"f6":19.913284,"f60":53.48088,"f61":26.910585,"f62":15.80046,"f63":8.972517,"f64":29.73437,"f65":44.574295,"f66":42.622276,"f67":47.29119,"f68":28.46356,"f69":7.6396303,"f7":24.765432,"f70":39.173985,"f71":30.7922,"f72":32.08839,"f73":60.616207,"f74":16.852234,"f75":28.30158,"f76":44.186314,"f77":12.135531,"f78":11.0508995,"f79":18.735733,"f8":38.52167,"f80":30.20231,"f81":32.560764,"f82":22.630316,"f83":24.01495,"f84":11.858848,"f85":36.73868,"f86":29.29584,"f87":16.457397,"f88":24.15614,"f89":30.76552,"f9":11.459825,"f90":30.113668,"f91":17.092823,"f92":44.543415,"f93":18.448896,"f94":24.860243,"f95":31.235786,"f96":14.717337,"f97":4.6042156,"f98":19.346577,"f99":22.666792},"BasicComponentDefs":{"Component 12":[{"ApiVersion":"v1/beta","Kind":"ComponentDefinition","Metadata":{"Name":"Implementation 12.1","Labels":{},"Annotations":null},"Spec":{"Workload":{"Type":"Container","Definition":{"ApiVersion":"","Kind":""}},"Schematic":{"Definition":{"name":"TestApp","image":"gitlab.ilabt.imec.be:4567/fledge/benchmark/dash:1.0.0-capstan","command":["./dashserver.so"],"resources":{"limits":{"cpu":"500m","memory":"300M"},"requests":{"cpu":"100m","memory":"100M"}},"imagePullPolicy":"Always"},"Params":null,"BaseComponent":"Component 12","BaseResources":null,"MaxResources":null}}}],"Component 26":[{"ApiVersion":"v1/beta","Kind":"ComponentDefinition","Metadata":{"Name":"Implementation 26.1","Labels":{},"Annotations":null},"Spec":{"Workload":{"Type":"Container","Definition":{"ApiVersion":"","Kind":""}},"Schematic":{"Definition":{"name":"TestApp","image":"gitlab.ilabt.imec.be:4567/fledge/benchmark/dash:1.0.0-capstan","command":["./dashserver.so"],"resources":{"limits":{"cpu":"500m","memory":"300M"},"requests":{"cpu":"100m","memory":"100M"}},"imagePullPolicy":"Always"},"Params":null,"BaseComponent":"Component 26","BaseResources":null,"MaxResources":null}}}],"Component 30":[{"ApiVersion":"v1/beta","Kind":"ComponentDefinition","Metadata":{"Name":"Implementation 30.2","Labels":{},"Annotations":null},"Spec":{"Workload":{"Type":"Container","Definition":{"ApiVersion":"","Kind":""}},"Schematic":{"Definition":{"name":"TestApp","image":"gitlab.ilabt.imec.be:4567/fledge/benchmark/dash:1.0.0-capstan","command":["./dashserver.so"],"resources":{"limits":{"cpu":"500m","memory":"300M"},"requests":{"cpu":"100m","memory":"100M"}},"imagePullPolicy":"Always"},"Params":null,"BaseComponent":"Component 30","BaseResources":null,"MaxResources":null}}}],"Component 42":[{"ApiVersion":"v1/beta","Kind":"ComponentDefinition","Metadata":{"Name":"Implementation 42.2","Labels":{},"Annotations":null},"Spec":{"Workload":{"Type":"Container","Definition":{"ApiVersion":"","Kind":""}},"Schematic":{"Definition":{"name":"TestApp","image":"gitlab.ilabt.imec.be:4567/fledge/benchmark/dash:1.0.0-capstan","command":["./dashserver.so"],"resources":{"limits":{"cpu":"500m","memory":"300M"},"requests":{"cpu":"100m","memory":"100M"}},"imagePullPolicy":"Always"},"Params":null,"BaseComponent":"Component 42","BaseResources":null,"MaxResources":null}}}],"Component 45":[{"ApiVersion":"v1/beta","Kind":"ComponentDefinition","Metadata":{"Name":"Implementation 45.2","Labels":{},"Annotations":null},"Spec":{"Workload":{"Type":"Container","Definition":{"ApiVersion":"","Kind":""}},"Schematic":{"Definition":{"name":"TestApp","image":"gitlab.ilabt.imec.be:4567/fledge/benchmark/dash:1.0.0-capstan","command":["./dashserver.so"],"resources":{"limits":{"cpu":"500m","memory":"300M"},"requests":{"cpu":"100m","memory":"100M"}},"imagePullPolicy":"Always"},"Params":null,"BaseComponent":"Component 45","BaseResources":null,"MaxResources":null}}}]}}