{"discoAPIPort":31052,"repoAPIPort":32052,"initialNodes":[{"name":"f0","ip":"127.0.0.1","distance":0,"discoAPIPort":31000,"repoAPIPort":32000},{"name":"f33","ip":"127.0.0.1","distance":0,"discoAPIPort":31033,"repoAPIPort":32033},{"name":"f31","ip":"127.0.0.1","distance":0,"discoAPIPort":31031,"repoAPIPort":32031},{"name":"f8","ip":"127.0.0.1","distance":0,"discoAPIPort":31008,"repoAPIPort":32008},{"name":"f50","ip":"127.0.0.1","distance":0,"discoAPIPort":31050,"repoAPIPort":32050}],"maxPing":20,"nodeID":"f52","nodeType":"servicenode","pingPeriod":3000,"testMode":true,"cheatyMinimalPing":10,"cheatyMinimalPingMap":{"e0":6.9169574,"f0":17.74166,"f1":32.218987,"f10":9.229398,"f100":10.799805,"f101":18.746746,"f102":29.019245,"f103":28.77538,"f104":32.38993,"f105":14.981128,"f106":17.024065,"f107":38.792133,"f108":31.836424,"f109":5.039477,"f11":13.963255,"f110":34.39034,"f111":18.697342,"f112":15.558138,"f113":33.139137,"f114":23.310486,"f115":23.007637,"f116":32.178146,"f117":11.336158,"f118":23.007008,"f119":17.509281,"f12":5.061784,"f120":33.652622,"f121":22.88397,"f122":31.159073,"f123":6.1168065,"f124":10.347165,"f125":28.50653,"f126":22.379286,"f127":33.020695,"f128":24.641214,"f129":3.9827833,"f13":20.754766,"f130":15.881904,"f131":21.035444,"f132":22.406109,"f133":17.582628,"f134":35.685734,"f135":15.891499,"f136":16.421629,"f137":22.326412,"f138":27.05511,"f139":34.446194,"f14":10.076147,"f140":15.215848,"f141":27.511703,"f142":13.82526,"f143":22.460266,"f144":15.142324,"f145":28.333282,"f146":37.756443,"f147":25.426868,"f148":33.980736,"f149":3.5283144,"f15":33.345734,"f150":20.632582,"f151":39.967426,"f152":8.624361,"f153":25.189892,"f154":27.263233,"f155":20.467121,"f156":26.10107,"f157":10.747378,"f158":23.58772,"f159":28.01601,"f16":16.19607,"f160":6.032168,"f161":28.752813,"f162":17.918455,"f163":24.892946,"f164":16.622372,"f165":27.104729,"f166":15.261983,"f167":13.286243,"f168":31.403158,"f169":12.483895,"f17":26.104815,"f170":27.116611,"f171":4.8196373,"f172":25.033781,"f173":22.21761,"f174":2.3841476,"f18":36.897877,"f19":14.755996,"f2":21.686584,"f20":31.391312,"f21":6.0797596,"f22":25.128065,"f23":12.961287,"f24":14.431867,"f25":26.687828,"f26":9.9911785,"f27":17.909174,"f28":15.099925,"f29":8.6918125,"f3":22.985851,"f30":25.580097,"f31":33.762646,"f32":28.867987,"f33":15.452079,"f34":26.409096,"f35":19.42634,"f36":23.653963,"f37":24.38041,"f38":39.67922,"f39":28.384954,"f4":10.522024,"f40":15.97479,"f41":5.817916,"f42":8.832985,"f43":34.27453,"f44":18.74303,"f45":16.04936,"f46":25.203655,"f47":30.836044,"f48":28.043398,"f49":14.601313,"f5":21.13491,"f50":4.472677,"f51":27.699835,"f53":30.851425,"f54":18.75412,"f55":20.90019,"f56":23.724586,"f57":26.450016,"f58":7.7505445,"f59":33.44971,"f6":21.78357,"f60":26.38298,"f61":14.028041,"f62":17.692038,"f63":23.515854,"f64":28.836546,"f65":21.26109,"f66":17.139553,"f67":16.693865,"f68":10.020897,"f69":23.420582,"f7":23.469656,"f70":22.169785,"f71":29.976677,"f72":22.325611,"f73":23.304564,"f74":17.775467,"f75":12.658714,"f76":9.990798,"f77":20.835728,"f78":29.606901,"f79":7.004315,"f8":22.742329,"f80":8.513678,"f81":10.428586,"f82":24.713186,"f83":25.185394,"f84":19.394875,"f85":18.275644,"f86":29.115088,"f87":21.415318,"f88":8.270795,"f89":4.435774,"f9":16.739466,"f90":3.3614314,"f91":9.956021,"f92":12.030787,"f93":27.643635,"f94":20.810621,"f95":7.1527686,"f96":22.900385,"f97":26.456394,"f98":23.14767,"f99":28.206692},"BasicComponentDefs":{"Component 17":[{"ApiVersion":"v1/beta","Kind":"ComponentDefinition","Metadata":{"Name":"Implementation 17.1","Labels":{},"Annotations":null},"Spec":{"Workload":{"Type":"Container","Definition":{"ApiVersion":"","Kind":""}},"Schematic":{"Definition":{"name":"TestApp","image":"gitlab.ilabt.imec.be:4567/fledge/benchmark/dash:1.0.0-capstan","command":["./dashserver.so"],"resources":{"limits":{"cpu":"500m","memory":"300M"},"requests":{"cpu":"100m","memory":"100M"}},"imagePullPolicy":"Always"},"Params":null,"BaseComponent":"Component 17","BaseResources":null,"MaxResources":null}}}],"Component 21":[{"ApiVersion":"v1/beta","Kind":"ComponentDefinition","Metadata":{"Name":"Implementation 21.1","Labels":{},"Annotations":null},"Spec":{"Workload":{"Type":"Container","Definition":{"ApiVersion":"","Kind":""}},"Schematic":{"Definition":{"name":"TestApp","image":"gitlab.ilabt.imec.be:4567/fledge/benchmark/dash:1.0.0-capstan","command":["./dashserver.so"],"resources":{"limits":{"cpu":"500m","memory":"300M"},"requests":{"cpu":"100m","memory":"100M"}},"imagePullPolicy":"Always"},"Params":null,"BaseComponent":"Component 21","BaseResources":null,"MaxResources":null}}}],"Component 25":[{"ApiVersion":"v1/beta","Kind":"ComponentDefinition","Metadata":{"Name":"Implementation 25.2","Labels":{},"Annotations":null},"Spec":{"Workload":{"Type":"Container","Definition":{"ApiVersion":"","Kind":""}},"Schematic":{"Definition":{"name":"TestApp","image":"gitlab.ilabt.imec.be:4567/fledge/benchmark/dash:1.0.0-capstan","command":["./dashserver.so"],"resources":{"limits":{"cpu":"500m","memory":"300M"},"requests":{"cpu":"100m","memory":"100M"}},"imagePullPolicy":"Always"},"Params":null,"BaseComponent":"Component 25","BaseResources":null,"MaxResources":null}}}],"Component 27":[{"ApiVersion":"v1/beta","Kind":"ComponentDefinition","Metadata":{"Name":"Implementation 27.1","Labels":{},"Annotations":null},"Spec":{"Workload":{"Type":"Container","Definition":{"ApiVersion":"","Kind":""}},"Schematic":{"Definition":{"name":"TestApp","image":"gitlab.ilabt.imec.be:4567/fledge/benchmark/dash:1.0.0-capstan","command":["./dashserver.so"],"resources":{"limits":{"cpu":"500m","memory":"300M"},"requests":{"cpu":"100m","memory":"100M"}},"imagePullPolicy":"Always"},"Params":null,"BaseComponent":"Component 27","BaseResources":null,"MaxResources":null}}}],"Component 4":[{"ApiVersion":"v1/beta","Kind":"ComponentDefinition","Metadata":{"Name":"Implementation 4.2","Labels":{},"Annotations":null},"Spec":{"Workload":{"Type":"Container","Definition":{"ApiVersion":"","Kind":""}},"Schematic":{"Definition":{"name":"TestApp","image":"gitlab.ilabt.imec.be:4567/fledge/benchmark/dash:1.0.0-capstan","command":["./dashserver.so"],"resources":{"limits":{"cpu":"500m","memory":"300M"},"requests":{"cpu":"100m","memory":"100M"}},"imagePullPolicy":"Always"},"Params":null,"BaseComponent":"Component 4","BaseResources":null,"MaxResources":null}}}]}}