{"discoAPIPort":31061,"repoAPIPort":32061,"initialNodes":[{"name":"f24","ip":"127.0.0.1","distance":0,"discoAPIPort":31024,"repoAPIPort":32024},{"name":"f0","ip":"127.0.0.1","distance":0,"discoAPIPort":31000,"repoAPIPort":32000},{"name":"f36","ip":"127.0.0.1","distance":0,"discoAPIPort":31036,"repoAPIPort":32036},{"name":"f0","ip":"127.0.0.1","distance":0,"discoAPIPort":31000,"repoAPIPort":32000},{"name":"f27","ip":"127.0.0.1","distance":0,"discoAPIPort":31027,"repoAPIPort":32027}],"maxPing":20,"nodeID":"f61","nodeType":"servicenode","pingPeriod":3000,"testMode":true,"cheatyMinimalPing":10,"cheatyMinimalPingMap":{"e0":13.586261,"f0":27.014267,"f1":42.66545,"f10":27.524452,"f100":9.530793,"f101":39.904335,"f102":6.2734985,"f103":43.97866,"f104":11.413708,"f105":14.606504,"f106":37.202473,"f107":26.685482,"f108":13.898425,"f109":20.540297,"f11":26.694841,"f110":28.66144,"f111":14.361239,"f112":25.52129,"f113":28.615253,"f114":39.340218,"f115":12.279555,"f116":5.7005215,"f117":11.246151,"f118":6.750049,"f119":5.2533765,"f12":30.652248,"f120":18.969751,"f121":28.766722,"f122":36.44769,"f123":6.4370685,"f124":23.21329,"f125":36.334423,"f126":5.640084,"f127":18.767683,"f128":34.870167,"f129":4.4744616,"f13":50.185036,"f130":12.143448,"f131":12.792264,"f132":20.955933,"f133":7.2090077,"f134":17.961363,"f135":21.812101,"f136":18.343029,"f137":20.729414,"f138":8.880996,"f139":34.387856,"f14":22.76629,"f140":36.865448,"f141":36.360188,"f142":19.397545,"f143":42.808395,"f144":5.6207843,"f145":33.36947,"f146":27.453913,"f147":30.22966,"f148":7.7437587,"f149":12.027491,"f15":9.589275,"f16":19.651056,"f17":12.803051,"f18":36.895653,"f19":20.069384,"f2":15.38921,"f20":16.329695,"f21":29.405394,"f22":13.9658,"f23":36.067795,"f24":35.818398,"f25":18.555302,"f26":22.995476,"f27":17.435165,"f28":22.77589,"f29":15.038175,"f3":25.206001,"f30":14.034758,"f31":35.245163,"f32":10.521511,"f33":38.067497,"f34":37.618786,"f35":28.115929,"f36":26.521776,"f37":12.283971,"f38":11.906324,"f39":11.323835,"f4":15.860962,"f40":21.689064,"f41":11.467452,"f42":21.74221,"f43":22.302729,"f44":13.343328,"f45":15.160095,"f46":20.941498,"f47":14.109001,"f48":12.393318,"f49":5.317604,"f5":25.870432,"f50":16.649923,"f51":22.935331,"f52":9.066184,"f53":6.2476673,"f54":26.053762,"f55":33.784466,"f56":35.990208,"f57":26.827847,"f58":43.717533,"f59":28.665598,"f6":15.36735,"f60":22.72794,"f62":18.506344,"f63":39.39187,"f64":30.0383,"f65":6.8963747,"f66":2.9439216,"f67":7.010094,"f68":30.055258,"f69":12.232265,"f7":29.642889,"f70":32.27079,"f71":13.078877,"f72":20.300066,"f73":39.5324,"f74":8.513501,"f75":31.686535,"f76":24.594576,"f77":50.52441,"f78":48.496696,"f79":38.009434,"f8":12.081934,"f80":32.176422,"f81":12.06986,"f82":21.832539,"f83":37.347103,"f84":39.784702,"f85":12.996506,"f86":12.66442,"f87":27.334082,"f88":22.557858,"f89":29.37669,"f9":14.563615,"f90":24.75595,"f91":29.496965,"f92":27.190992,"f93":18.98055,"f94":13.022684,"f95":30.725143,"f96":37.18475,"f97":6.0057755,"f98":10.425959,"f99":25.709795},"BasicComponentDefs":{"Component 16":[{"ApiVersion":"v1/beta","Kind":"ComponentDefinition","Metadata":{"Name":"Implementation 16.2","Labels":{},"Annotations":null},"Spec":{"Workload":{"Type":"Container","Definition":{"ApiVersion":"","Kind":""}},"Schematic":{"Definition":{"name":"TestApp","image":"gitlab.ilabt.imec.be:4567/fledge/benchmark/dash:1.0.0-capstan","command":["./dashserver.so"],"resources":{"limits":{"cpu":"500m","memory":"300M"},"requests":{"cpu":"100m","memory":"100M"}},"imagePullPolicy":"Always"},"Params":null,"BaseComponent":"Component 16","BaseResources":null,"MaxResources":null}}}],"Component 20":[{"ApiVersion":"v1/beta","Kind":"ComponentDefinition","Metadata":{"Name":"Implementation 20.1","Labels":{},"Annotations":null},"Spec":{"Workload":{"Type":"Container","Definition":{"ApiVersion":"","Kind":""}},"Schematic":{"Definition":{"name":"TestApp","image":"gitlab.ilabt.imec.be:4567/fledge/benchmark/dash:1.0.0-capstan","command":["./dashserver.so"],"resources":{"limits":{"cpu":"500m","memory":"300M"},"requests":{"cpu":"100m","memory":"100M"}},"imagePullPolicy":"Always"},"Params":null,"BaseComponent":"Component 20","BaseResources":null,"MaxResources":null}}},{"ApiVersion":"v1/beta","Kind":"ComponentDefinition","Metadata":{"Name":"Implementation 20.2","Labels":{},"Annotations":null},"Spec":{"Workload":{"Type":"Container","Definition":{"ApiVersion":"","Kind":""}},"Schematic":{"Definition":{"name":"TestApp","image":"gitlab.ilabt.imec.be:4567/fledge/benchmark/dash:1.0.0-capstan","command":["./dashserver.so"],"resources":{"limits":{"cpu":"500m","memory":"300M"},"requests":{"cpu":"100m","memory":"100M"}},"imagePullPolicy":"Always"},"Params":null,"BaseComponent":"Component 20","BaseResources":null,"MaxResources":null}}}],"Component 4":[{"ApiVersion":"v1/beta","Kind":"ComponentDefinition","Metadata":{"Name":"Implementation 4.1","Labels":{},"Annotations":null},"Spec":{"Workload":{"Type":"Container","Definition":{"ApiVersion":"","Kind":""}},"Schematic":{"Definition":{"name":"TestApp","image":"gitlab.ilabt.imec.be:4567/fledge/benchmark/dash:1.0.0-capstan","command":["./dashserver.so"],"resources":{"limits":{"cpu":"500m","memory":"300M"},"requests":{"cpu":"100m","memory":"100M"}},"imagePullPolicy":"Always"},"Params":null,"BaseComponent":"Component 4","BaseResources":null,"MaxResources":null}}}],"Component 48":[{"ApiVersion":"v1/beta","Kind":"ComponentDefinition","Metadata":{"Name":"Implementation 48.2","Labels":{},"Annotations":null},"Spec":{"Workload":{"Type":"Container","Definition":{"ApiVersion":"","Kind":""}},"Schematic":{"Definition":{"name":"TestApp","image":"gitlab.ilabt.imec.be:4567/fledge/benchmark/dash:1.0.0-capstan","command":["./dashserver.so"],"resources":{"limits":{"cpu":"500m","memory":"300M"},"requests":{"cpu":"100m","memory":"100M"}},"imagePullPolicy":"Always"},"Params":null,"BaseComponent":"Component 48","BaseResources":null,"MaxResources":null}}}]}}