{"discoAPIPort":31053,"repoAPIPort":32053,"initialNodes":[{"name":"f5","ip":"127.0.0.1","distance":0,"discoAPIPort":31005,"repoAPIPort":32005},{"name":"f10","ip":"127.0.0.1","distance":0,"discoAPIPort":31010,"repoAPIPort":32010},{"name":"f29","ip":"127.0.0.1","distance":0,"discoAPIPort":31029,"repoAPIPort":32029},{"name":"f7","ip":"127.0.0.1","distance":0,"discoAPIPort":31007,"repoAPIPort":32007},{"name":"f34","ip":"127.0.0.1","distance":0,"discoAPIPort":31034,"repoAPIPort":32034}],"maxPing":20,"nodeID":"f53","nodeType":"servicenode","pingPeriod":3000,"testMode":true,"cheatyMinimalPing":10,"cheatyMinimalPingMap":{"e0":16.097761,"f0":21.30891,"f1":35.61382,"f10":21.099823,"f100":32.50788,"f101":31.933807,"f102":25.144373,"f103":37.38909,"f104":11.877891,"f105":34.973656,"f106":32.690125,"f107":33.896915,"f108":23.218622,"f109":28.684713,"f11":16.230337,"f110":19.54373,"f111":13.843897,"f112":9.527961,"f113":11.403088,"f114":17.549583,"f115":33.097694,"f116":22.13765,"f117":17.321468,"f118":13.930867,"f119":24.04857,"f12":43.911224,"f120":30.236513,"f121":3.6604438,"f122":46.867863,"f123":26.399237,"f124":35.868553,"f125":32.72861,"f126":18.085697,"f127":31.96931,"f128":7.662462,"f129":16.117798,"f13":26.328062,"f130":11.719283,"f131":19.839716,"f132":16.749598,"f133":20.04624,"f134":7.8950324,"f135":23.191292,"f136":17.136774,"f137":24.77327,"f138":10.7906,"f139":16.72564,"f14":7.253447,"f140":11.411983,"f141":23.147547,"f142":20.692493,"f143":34.936066,"f144":27.582685,"f145":35.653027,"f146":30.361645,"f147":17.164997,"f148":13.810589,"f149":10.216793,"f15":8.39881,"f16":11.33252,"f17":18.238132,"f18":14.587039,"f19":8.81222,"f2":20.063343,"f20":24.076809,"f21":29.557468,"f22":20.39159,"f23":21.433102,"f24":13.293032,"f25":14.816149,"f26":10.966845,"f27":23.179766,"f28":15.894883,"f29":18.6611,"f3":31.332205,"f30":35.653347,"f31":20.87183,"f32":43.092186,"f33":15.337133,"f34":31.515106,"f35":14.171904,"f36":8.662038,"f37":12.929776,"f38":6.284669,"f39":41.86422,"f4":6.947105,"f40":32.738476,"f41":16.007904,"f42":23.91404,"f43":10.130316,"f44":17.86568,"f45":8.48444,"f46":17.826406,"f47":17.282173,"f48":9.949833,"f49":10.920872,"f5":21.011345,"f50":29.426952,"f51":5.578996,"f52":12.254748,"f54":34.885654,"f55":29.619131,"f56":24.042831,"f57":25.155214,"f58":40.554,"f59":27.456957,"f6":22.166157,"f60":29.486618,"f61":1.2472292,"f62":16.353613,"f63":15.146902,"f64":14.64666,"f65":23.400425,"f66":13.762457,"f67":16.567415,"f68":19.861254,"f69":14.639199,"f7":13.190359,"f70":41.540794,"f71":17.70512,"f72":15.885931,"f73":19.380165,"f74":36.499367,"f75":18.949312,"f76":17.559526,"f77":39.468636,"f78":32.540688,"f79":17.72819,"f8":8.789887,"f80":14.561334,"f81":8.80785,"f82":22.602291,"f83":14.71329,"f84":28.826698,"f85":23.207813,"f86":41.847527,"f87":11.861911,"f88":15.292286,"f89":20.025433,"f9":25.350744,"f90":29.388885,"f91":32.167236,"f92":11.627169,"f93":20.09646,"f94":15.432065,"f95":23.848866,"f96":11.082799,"f97":21.489777,"f98":15.402253,"f99":9.244228},"BasicComponentDefs":{"Component 11":[{"ApiVersion":"v1/beta","Kind":"ComponentDefinition","Metadata":{"Name":"Implementation 11.2","Labels":{},"Annotations":null},"Spec":{"Workload":{"Type":"Container","Definition":{"ApiVersion":"","Kind":""}},"Schematic":{"Definition":{"name":"TestApp","image":"gitlab.ilabt.imec.be:4567/fledge/benchmark/dash:1.0.0-capstan","command":["./dashserver.so"],"resources":{"limits":{"cpu":"500m","memory":"300M"},"requests":{"cpu":"100m","memory":"100M"}},"imagePullPolicy":"Always"},"Params":null,"BaseComponent":"Component 11","BaseResources":null,"MaxResources":null}}}],"Component 34":[{"ApiVersion":"v1/beta","Kind":"ComponentDefinition","Metadata":{"Name":"Implementation 34.2","Labels":{},"Annotations":null},"Spec":{"Workload":{"Type":"Container","Definition":{"ApiVersion":"","Kind":""}},"Schematic":{"Definition":{"name":"TestApp","image":"gitlab.ilabt.imec.be:4567/fledge/benchmark/dash:1.0.0-capstan","command":["./dashserver.so"],"resources":{"limits":{"cpu":"500m","memory":"300M"},"requests":{"cpu":"100m","memory":"100M"}},"imagePullPolicy":"Always"},"Params":null,"BaseComponent":"Component 34","BaseResources":null,"MaxResources":null}}}],"Component 41":[{"ApiVersion":"v1/beta","Kind":"ComponentDefinition","Metadata":{"Name":"Implementation 41.2","Labels":{},"Annotations":null},"Spec":{"Workload":{"Type":"Container","Definition":{"ApiVersion":"","Kind":""}},"Schematic":{"Definition":{"name":"TestApp","image":"gitlab.ilabt.imec.be:4567/fledge/benchmark/dash:1.0.0-capstan","command":["./dashserver.so"],"resources":{"limits":{"cpu":"500m","memory":"300M"},"requests":{"cpu":"100m","memory":"100M"}},"imagePullPolicy":"Always"},"Params":null,"BaseComponent":"Component 41","BaseResources":null,"MaxResources":null}}},{"ApiVersion":"v1/beta","Kind":"ComponentDefinition","Metadata":{"Name":"Implementation 41.1","Labels":{},"Annotations":null},"Spec":{"Workload":{"Type":"Container","Definition":{"ApiVersion":"","Kind":""}},"Schematic":{"Definition":{"name":"TestApp","image":"gitlab.ilabt.imec.be:4567/fledge/benchmark/dash:1.0.0-capstan","command":["./dashserver.so"],"resources":{"limits":{"cpu":"500m","memory":"300M"},"requests":{"cpu":"100m","memory":"100M"}},"imagePullPolicy":"Always"},"Params":null,"BaseComponent":"Component 41","BaseResources":null,"MaxResources":null}}}],"Component 44":[{"ApiVersion":"v1/beta","Kind":"ComponentDefinition","Metadata":{"Name":"Implementation 44.1","Labels":{},"Annotations":null},"Spec":{"Workload":{"Type":"Container","Definition":{"ApiVersion":"","Kind":""}},"Schematic":{"Definition":{"name":"TestApp","image":"gitlab.ilabt.imec.be:4567/fledge/benchmark/dash:1.0.0-capstan","command":["./dashserver.so"],"resources":{"limits":{"cpu":"500m","memory":"300M"},"requests":{"cpu":"100m","memory":"100M"}},"imagePullPolicy":"Always"},"Params":null,"BaseComponent":"Component 44","BaseResources":null,"MaxResources":null}}}]}}